{
  "metadata": {
    "collected_at": "2025-10-01T22:24:38.234056",
    "records_count": 1,
    "api_usage": 2816,
    "daily_limit": 7500
  },
  "data": {
    "fixture_info": {
      "id": 1035102,
      "date": "2023-09-30T14:00:00+00:00",
      "home_team": "Newcastle",
      "away_team": "Burnley",
      "score": {
        "home": 2,
        "away": 0
      }
    },
    "events": [
      {
        "time": {
          "elapsed": 14,
          "extra": null
        },
        "team": {
          "id": 34,
          "name": "Newcastle",
          "logo": "https://media.api-sports.io/football/teams/34.png"
        },
        "player": {
          "id": 2507,
          "name": "M. Almirón"
        },
        "assist": {
          "id": 169,
          "name": "K. Trippier"
        },
        "type": "Goal",
        "detail": "Normal Goal",
        "comments": null
      },
      {
        "time": {
          "elapsed": 17,
          "extra": null
        },
        "team": {
          "id": 34,
          "name": "Newcastle",
          "logo": "https://media.api-sports.io/football/teams/34.png"
        },
        "player": {
          "id": 138787,
          "name": "Anthony Gordon"
        },
        "assist": {
          "id": null,
          "name": null
        },
        "type": "Card",
        "detail": "Yellow Card",
        "comments": "Time wasting"
      },
      {
        "time": {
          "elapsed": 29,
          "extra": null
        },
        "team": {
          "id": 44,
          "name": "Burnley",
          "logo": "https://media.api-sports.io/football/teams/44.png"
        },
        "player": {
          "id": 123469,
          "name": "Zeki Amdouni"
        },
        "assist": {
          "id": null,
          "name": null
        },
        "type": "Card",
        "detail": "Yellow Card",
        "comments": "Foul"
      },
      {
        "time": {
          "elapsed": 40,
          "extra": null
        },
        "team": {
          "id": 44,
          "name": "Burnley",
          "logo": "https://media.api-sports.io/football/teams/44.png"
        },
        "player": {
          "id": 25628,
          "name": "Jordan Beyer"
        },
        "assist": {
          "id": null,
          "name": null
        },
        "type": "Card",
        "detail": "Yellow Card",
        "comments": "Foul"
      },
      {
        "time": {
          "elapsed": 53,
          "extra": null
        },
        "team": {
          "id": 44,
          "name": "Burnley",
          "logo": "https://media.api-sports.io/football/teams/44.png"
        },
        "player": {
          "id": 18918,
          "name": "Charlie Taylor"
        },
        "assist": {
          "id": null,
          "name": null
        },
        "type": "Card",
        "detail": "Yellow Card",
        "comments": "Foul"
      },
      {
        "time": {
          "elapsed": 58,
          "extra": null
        },
        "team": {
          "id": 44,
          "name": "Burnley",
          "logo": "https://media.api-sports.io/football/teams/44.png"
        },
        "player": {
          "id": 359603,
          "name": "L. Koleosho"
        },
        "assist": {
          "id": 22,
          "name": "J. Bruun Larsen"
        },
        "type": "subst",
        "detail": "Substitution 1",
        "comments": null
      },
      {
        "time": {
          "elapsed": 58,
          "extra": null
        },
        "team": {
          "id": 44,
          "name": "Burnley",
          "logo": "https://media.api-sports.io/football/teams/44.png"
        },
        "player": {
          "id": 123469,
          "name": "Z. Amdouni"
        },
        "assist": {
          "id": 19169,
          "name": "J. Rodríguez"
        },
        "type": "subst",
        "detail": "Substitution 2",
        "comments": null
      },
      {
        "time": {
          "elapsed": 64,
          "extra": null
        },
        "team": {
          "id": 34,
          "name": "Newcastle",
          "logo": "https://media.api-sports.io/football/teams/34.png"
        },
        "player": {
          "id": 138908,
          "name": "E. Anderson"
        },
        "assist": {
          "id": 723,
          "name": "Joelinton"
        },
        "type": "subst",
        "detail": "Substitution 1",
        "comments": null
      },
      {
        "time": {
          "elapsed": 67,
          "extra": null
        },
        "team": {
          "id": 44,
          "name": "Burnley",
          "logo": "https://media.api-sports.io/football/teams/44.png"
        },
        "player": {
          "id": 278079,
          "name": "A. Ramsey"
        },
        "assist": {
          "id": 336564,
          "name": "W. Odobert"
        },
        "type": "subst",
        "detail": "Substitution 3",
        "comments": null
      },
      {
        "time": {
          "elapsed": 68,
          "extra": null
        },
        "team": {
          "id": 34,
          "name": "Newcastle",
          "logo": "https://media.api-sports.io/football/teams/34.png"
        },
        "player": {
          "id": 723,
          "name": "Joelinton"
        },
        "assist": {
          "id": 31146,
          "name": "S. Tonali"
        },
        "type": "subst",
        "detail": "Substitution 2",
        "comments": null
      },
      {
        "time": {
          "elapsed": 76,
          "extra": null
        },
        "team": {
          "id": 34,
          "name": "Newcastle",
          "logo": "https://media.api-sports.io/football/teams/34.png"
        },
        "player": {
          "id": 2864,
          "name": "A. Isak"
        },
        "assist": {
          "id": null,
          "name": null
        },
        "type": "Goal",
        "detail": "Penalty",
        "comments": null
      },
      {
        "time": {
          "elapsed": 88,
          "extra": null
        },
        "team": {
          "id": 44,
          "name": "Burnley",
          "logo": "https://media.api-sports.io/football/teams/44.png"
        },
        "player": {
          "id": 1934,
          "name": "S. Berge"
        },
        "assist": {
          "id": 129169,
          "name": "A. Zaroury"
        },
        "type": "subst",
        "detail": "Substitution 4",
        "comments": null
      },
      {
        "time": {
          "elapsed": 88,
          "extra": null
        },
        "team": {
          "id": 44,
          "name": "Burnley",
          "logo": "https://media.api-sports.io/football/teams/44.png"
        },
        "player": {
          "id": 19331,
          "name": "C. Roberts"
        },
        "assist": {
          "id": 8661,
          "name": "Vitinho"
        },
        "type": "subst",
        "detail": "Substitution 5",
        "comments": null
      },
      {
        "time": {
          "elapsed": 90,
          "extra": 6
        },
        "team": {
          "id": 34,
          "name": "Newcastle",
          "logo": "https://media.api-sports.io/football/teams/34.png"
        },
        "player": {
          "id": 2507,
          "name": "M. Almirón"
        },
        "assist": {
          "id": 19163,
          "name": "J. Murphy"
        },
        "type": "subst",
        "detail": "Substitution 3",
        "comments": null
      },
      {
        "time": {
          "elapsed": 90,
          "extra": 6
        },
        "team": {
          "id": 34,
          "name": "Newcastle",
          "logo": "https://media.api-sports.io/football/teams/34.png"
        },
        "player": {
          "id": 2864,
          "name": "A. Isak"
        },
        "assist": {
          "id": 158694,
          "name": "T. Livramento"
        },
        "type": "subst",
        "detail": "Substitution 4",
        "comments": null
      }
    ]
  }
}