{
  "metadata": {
    "collected_at": "2025-10-10T19:40:40.699753",
    "records_count": 1,
    "api_usage": 785,
    "daily_limit": 7500
  },
  "data": {
    "fixture_info": {
      "id": 592857,
      "date": "2021-05-19T19:15:00+00:00",
      "home_team": "Burnley",
      "away_team": "Liverpool",
      "score": {
        "home": 0,
        "away": 3
      }
    },
    "events": [
      {
        "time": {
          "elapsed": 43,
          "extra": null
        },
        "team": {
          "id": 40,
          "name": "Liverpool",
          "logo": "https://media.api-sports.io/football/teams/40.png"
        },
        "player": {
          "id": 302,
          "name": "R. Firmino"
        },
        "assist": {
          "id": 289,
          "name": "A. Robertson"
        },
        "type": "Goal",
        "detail": "Normal Goal",
        "comments": null
      },
      {
        "time": {
          "elapsed": 52,
          "extra": null
        },
        "team": {
          "id": 40,
          "name": "Liverpool",
          "logo": "https://media.api-sports.io/football/teams/40.png"
        },
        "player": {
          "id": 127472,
          "name": "N. Phillips"
        },
        "assist": {
          "id": 304,
          "name": "S. Mane"
        },
        "type": "Goal",
        "detail": "Normal Goal",
        "comments": null
      },
      {
        "time": {
          "elapsed": 76,
          "extra": null
        },
        "team": {
          "id": 44,
          "name": "Burnley",
          "logo": "https://media.api-sports.io/football/teams/44.png"
        },
        "player": {
          "id": 18930,
          "name": "M. Vydra"
        },
        "assist": {
          "id": 18922,
          "name": "J. Cork"
        },
        "type": "subst",
        "detail": "Substitution 1",
        "comments": null
      },
      {
        "time": {
          "elapsed": 81,
          "extra": null
        },
        "team": {
          "id": 40,
          "name": "Liverpool",
          "logo": "https://media.api-sports.io/football/teams/40.png"
        },
        "player": {
          "id": 297,
          "name": "A. Oxlade-Chamberlain"
        },
        "assist": {
          "id": 302,
          "name": "R. Firmino"
        },
        "type": "subst",
        "detail": "Substitution 1",
        "comments": null
      },
      {
        "time": {
          "elapsed": 87,
          "extra": null
        },
        "team": {
          "id": 40,
          "name": "Liverpool",
          "logo": "https://media.api-sports.io/football/teams/40.png"
        },
        "player": {
          "id": 296,
          "name": "J. Milner"
        },
        "assist": {
          "id": 300,
          "name": "G. Wijnaldum"
        },
        "type": "subst",
        "detail": "Substitution 2",
        "comments": null
      },
      {
        "time": {
          "elapsed": 88,
          "extra": null
        },
        "team": {
          "id": 40,
          "name": "Liverpool",
          "logo": "https://media.api-sports.io/football/teams/40.png"
        },
        "player": {
          "id": 297,
          "name": "A. Oxlade-Chamberlain"
        },
        "assist": {
          "id": 289,
          "name": "A. Robertson"
        },
        "type": "Goal",
        "detail": "Normal Goal",
        "comments": null
      },
      {
        "time": {
          "elapsed": 90,
          "extra": 2
        },
        "team": {
          "id": 40,
          "name": "Liverpool",
          "logo": "https://media.api-sports.io/football/teams/40.png"
        },
        "player": {
          "id": 1600,
          "name": "K. Tsimikas"
        },
        "assist": {
          "id": 304,
          "name": "S. Mane"
        },
        "type": "subst",
        "detail": "Substitution 3",
        "comments": null
      }
    ]
  }
}