{
  "metadata": {
    "collected_at": "2025-10-10T19:43:25.300417",
    "records_count": 1,
    "api_usage": 1608,
    "daily_limit": 7500
  },
  "data": {
    "fixture_info": {
      "id": 868055,
      "date": "2022-10-15T14:00:00+00:00",
      "home_team": "Wolves",
      "away_team": "Nottingham Forest",
      "score": {
        "home": 1,
        "away": 0
      }
    },
    "events": [
      {
        "time": {
          "elapsed": 16,
          "extra": null
        },
        "team": {
          "id": 65,
          "name": "Nottingham Forest",
          "logo": "https://media.api-sports.io/football/teams/65.png"
        },
        "player": {
          "id": 80,
          "name": "Emmanuel Dennis"
        },
        "assist": {
          "id": null,
          "name": null
        },
        "type": "Card",
        "detail": "Yellow Card",
        "comments": "Foul"
      },
      {
        "time": {
          "elapsed": 53,
          "extra": null
        },
        "team": {
          "id": 39,
          "name": "Wolves",
          "logo": "https://media.api-sports.io/football/teams/39.png"
        },
        "player": {
          "id": 18753,
          "name": "Adama Traoré"
        },
        "assist": {
          "id": null,
          "name": null
        },
        "type": "Var",
        "detail": "Penalty confirmed",
        "comments": null
      },
      {
        "time": {
          "elapsed": 56,
          "extra": null
        },
        "team": {
          "id": 39,
          "name": "Wolves",
          "logo": "https://media.api-sports.io/football/teams/39.png"
        },
        "player": {
          "id": 2676,
          "name": "Rúben Neves"
        },
        "assist": {
          "id": null,
          "name": null
        },
        "type": "Goal",
        "detail": "Penalty",
        "comments": null
      },
      {
        "time": {
          "elapsed": 67,
          "extra": null
        },
        "team": {
          "id": 65,
          "name": "Nottingham Forest",
          "logo": "https://media.api-sports.io/football/teams/65.png"
        },
        "player": {
          "id": 44811,
          "name": "Scott McKenna"
        },
        "assist": {
          "id": null,
          "name": null
        },
        "type": "Card",
        "detail": "Yellow Card",
        "comments": "Foul"
      },
      {
        "time": {
          "elapsed": 70,
          "extra": null
        },
        "team": {
          "id": 65,
          "name": "Nottingham Forest",
          "logo": "https://media.api-sports.io/football/teams/65.png"
        },
        "player": {
          "id": 2991,
          "name": "C. Kouyaté"
        },
        "assist": {
          "id": 24882,
          "name": "O. Mangala"
        },
        "type": "subst",
        "detail": "Substitution 1",
        "comments": null
      },
      {
        "time": {
          "elapsed": 70,
          "extra": null
        },
        "team": {
          "id": 65,
          "name": "Nottingham Forest",
          "logo": "https://media.api-sports.io/football/teams/65.png"
        },
        "player": {
          "id": 80,
          "name": "E. Dennis"
        },
        "assist": {
          "id": 900,
          "name": "J. Lingard"
        },
        "type": "subst",
        "detail": "Substitution 2",
        "comments": null
      },
      {
        "time": {
          "elapsed": 77,
          "extra": null
        },
        "team": {
          "id": 65,
          "name": "Nottingham Forest",
          "logo": "https://media.api-sports.io/football/teams/65.png"
        },
        "player": {
          "id": 19305,
          "name": "Ryan Yates"
        },
        "assist": {
          "id": null,
          "name": null
        },
        "type": "Var",
        "detail": "Penalty confirmed",
        "comments": null
      },
      {
        "time": {
          "elapsed": 80,
          "extra": null
        },
        "team": {
          "id": 39,
          "name": "Wolves",
          "logo": "https://media.api-sports.io/football/teams/39.png"
        },
        "player": {
          "id": 1605,
          "name": "Daniel Podence"
        },
        "assist": {
          "id": null,
          "name": null
        },
        "type": "Card",
        "detail": "Yellow Card",
        "comments": "Time wasting"
      },
      {
        "time": {
          "elapsed": 82,
          "extra": null
        },
        "team": {
          "id": 39,
          "name": "Wolves",
          "logo": "https://media.api-sports.io/football/teams/39.png"
        },
        "player": {
          "id": 54,
          "name": "Diego Costa"
        },
        "assist": {
          "id": 24888,
          "name": "Hwang Hee-Chan"
        },
        "type": "subst",
        "detail": "Substitution 1",
        "comments": null
      },
      {
        "time": {
          "elapsed": 82,
          "extra": null
        },
        "team": {
          "id": 39,
          "name": "Wolves",
          "logo": "https://media.api-sports.io/football/teams/39.png"
        },
        "player": {
          "id": 2677,
          "name": "João Moutinho"
        },
        "assist": {
          "id": 157912,
          "name": "B. Traoré"
        },
        "type": "subst",
        "detail": "Substitution 2",
        "comments": null
      },
      {
        "time": {
          "elapsed": 84,
          "extra": null
        },
        "team": {
          "id": 65,
          "name": "Nottingham Forest",
          "logo": "https://media.api-sports.io/football/teams/65.png"
        },
        "player": {
          "id": 2807,
          "name": "R. Freuler"
        },
        "assist": {
          "id": 8598,
          "name": "T. Awoniyi"
        },
        "type": "subst",
        "detail": "Substitution 3",
        "comments": null
      },
      {
        "time": {
          "elapsed": 85,
          "extra": null
        },
        "team": {
          "id": 39,
          "name": "Wolves",
          "logo": "https://media.api-sports.io/football/teams/39.png"
        },
        "player": {
          "id": 18753,
          "name": "Adama Traoré"
        },
        "assist": {
          "id": 130,
          "name": "Nélson Semedo"
        },
        "type": "subst",
        "detail": "Substitution 3",
        "comments": null
      },
      {
        "time": {
          "elapsed": 89,
          "extra": null
        },
        "team": {
          "id": 65,
          "name": "Nottingham Forest",
          "logo": "https://media.api-sports.io/football/teams/65.png"
        },
        "player": {
          "id": 17365,
          "name": "H. Toffolo"
        },
        "assist": {
          "id": 18884,
          "name": "S. Surridge"
        },
        "type": "subst",
        "detail": "Substitution 4",
        "comments": null
      },
      {
        "time": {
          "elapsed": 90,
          "extra": 7
        },
        "team": {
          "id": 39,
          "name": "Wolves",
          "logo": "https://media.api-sports.io/football/teams/39.png"
        },
        "player": {
          "id": 204033,
          "name": "Joe Hodge"
        },
        "assist": {
          "id": null,
          "name": null
        },
        "type": "Card",
        "detail": "Yellow Card",
        "comments": "Foul"
      },
      {
        "time": {
          "elapsed": 90,
          "extra": 2
        },
        "team": {
          "id": 39,
          "name": "Wolves",
          "logo": "https://media.api-sports.io/football/teams/39.png"
        },
        "player": {
          "id": 21138,
          "name": "R. Aït Nouri"
        },
        "assist": {
          "id": 280687,
          "name": "Hugo Bueno"
        },
        "type": "subst",
        "detail": "Substitution 4",
        "comments": null
      },
      {
        "time": {
          "elapsed": 90,
          "extra": 2
        },
        "team": {
          "id": 39,
          "name": "Wolves",
          "logo": "https://media.api-sports.io/football/teams/39.png"
        },
        "player": {
          "id": 41621,
          "name": "Matheus Nunes"
        },
        "assist": {
          "id": 204033,
          "name": "J. Hodge"
        },
        "type": "subst",
        "detail": "Substitution 5",
        "comments": null
      }
    ]
  }
}