{
  "metadata": {
    "collected_at": "2025-10-01T22:20:19.484261",
    "records_count": 1,
    "api_usage": 1091,
    "daily_limit": 7500
  },
  "data": {
    "fixture_info": {
      "id": 710813,
      "date": "2022-02-19T15:00:00+00:00",
      "home_team": "Southampton",
      "away_team": "Everton",
      "score": {
        "home": 2,
        "away": 0
      },
      "status": "FT"
    },
    "lineups": [
      {
        "team": {
          "id": 41,
          "name": "Southampton",
          "logo": "https://media.api-sports.io/football/teams/41.png",
          "colors": {
            "player": {
              "primary": "ff0000",
              "number": "ffffff",
              "border": "00ff1e"
            },
            "goalkeeper": {
              "primary": "00ff1e",
              "number": "ffffff",
              "border": "00ff1e"
            }
          }
        },
        "coach": {
          "id": 8,
          "name": "R. Hasenhüttl",
          "photo": "https://media.api-sports.io/football/coachs/8.png"
        },
        "formation": "4-4-2",
        "startXI": [
          {
            "player": {
              "id": 18932,
              "name": "F. Forster",
              "number": 44,
              "pos": "G",
              "grid": "1:1"
            }
          },
          {
            "player": {
              "id": 2999,
              "name": "J. Bednarek",
              "number": 35,
              "pos": "D",
              "grid": "2:4"
            }
          },
          {
            "player": {
              "id": 171,
              "name": "K. Walker-Peters",
              "number": 2,
              "pos": "D",
              "grid": "2:3"
            }
          },
          {
            "player": {
              "id": 158694,
              "name": "V. Livramento",
              "number": 21,
              "pos": "D",
              "grid": "2:2"
            }
          },
          {
            "player": {
              "id": 47480,
              "name": "M. Salisu",
              "number": 22,
              "pos": "D",
              "grid": "2:1"
            }
          },
          {
            "player": {
              "id": 18949,
              "name": "Oriol Romeu",
              "number": 6,
              "pos": "M",
              "grid": "3:4"
            }
          },
          {
            "player": {
              "id": 18945,
              "name": "S. Armstrong",
              "number": 17,
              "pos": "M",
              "grid": "3:3"
            }
          },
          {
            "player": {
              "id": 18946,
              "name": "M. Elyounoussi",
              "number": 24,
              "pos": "M",
              "grid": "3:2"
            }
          },
          {
            "player": {
              "id": 2938,
              "name": "J. Ward-Prowse",
              "number": 8,
              "pos": "M",
              "grid": "3:1"
            }
          },
          {
            "player": {
              "id": 19524,
              "name": "C. Adams",
              "number": 10,
              "pos": "F",
              "grid": "4:2"
            }
          },
          {
            "player": {
              "id": 138822,
              "name": "A. Broja",
              "number": 18,
              "pos": "F",
              "grid": "4:1"
            }
          }
        ],
        "substitutes": [
          {
            "player": {
              "id": 18956,
              "name": "S. Long",
              "number": 7,
              "pos": "F",
              "grid": null
            }
          },
          {
            "player": {
              "id": 2114,
              "name": "M. Djenepo",
              "number": 19,
              "pos": "M",
              "grid": null
            }
          },
          {
            "player": {
              "id": 19484,
              "name": "A. Armstrong",
              "number": 9,
              "pos": "F",
              "grid": null
            }
          },
          {
            "player": {
              "id": 18769,
              "name": "T. Walcott",
              "number": 32,
              "pos": "F",
              "grid": null
            }
          },
          {
            "player": {
              "id": 18940,
              "name": "J. Stephens",
              "number": 5,
              "pos": "D",
              "grid": null
            }
          },
          {
            "player": {
              "id": 130421,
              "name": "W. Smallbone",
              "number": 20,
              "pos": "M",
              "grid": null
            }
          },
          {
            "player": {
              "id": 18942,
              "name": "Y. Valery",
              "number": 43,
              "pos": "D",
              "grid": null
            }
          },
          {
            "player": {
              "id": 20557,
              "name": "I. Diallo",
              "number": 27,
              "pos": "M",
              "grid": null
            }
          },
          {
            "player": {
              "id": 2275,
              "name": "W. Caballero",
              "number": 13,
              "pos": "G",
              "grid": null
            }
          }
        ]
      },
      {
        "team": {
          "id": 45,
          "name": "Everton",
          "logo": "https://media.api-sports.io/football/teams/45.png",
          "colors": {
            "player": {
              "primary": "174a94",
              "number": "ffffff",
              "border": "54a121"
            },
            "goalkeeper": {
              "primary": "54a121",
              "number": "ffffff",
              "border": "54a121"
            }
          }
        },
        "coach": {
          "id": 20,
          "name": "F. Lampard",
          "photo": "https://media.api-sports.io/football/coachs/20.png"
        },
        "formation": "4-4-2",
        "startXI": [
          {
            "player": {
              "id": 2932,
              "name": "J. Pickford",
              "number": 1,
              "pos": "G",
              "grid": "1:1"
            }
          },
          {
            "player": {
              "id": 18758,
              "name": "S. Coleman",
              "number": 23,
              "pos": "D",
              "grid": "2:4"
            }
          },
          {
            "player": {
              "id": 2934,
              "name": "M. Keane",
              "number": 5,
              "pos": "D",
              "grid": "2:3"
            }
          },
          {
            "player": {
              "id": 18760,
              "name": "J. Kenny",
              "number": 2,
              "pos": "D",
              "grid": "2:2"
            }
          },
          {
            "player": {
              "id": 19150,
              "name": "M. Holgate",
              "number": 4,
              "pos": "D",
              "grid": "2:1"
            }
          },
          {
            "player": {
              "id": 326,
              "name": "Allan",
              "number": 6,
              "pos": "M",
              "grid": "3:4"
            }
          },
          {
            "player": {
              "id": 547,
              "name": "D. van de Beek",
              "number": 30,
              "pos": "M",
              "grid": "3:3"
            }
          },
          {
            "player": {
              "id": 1455,
              "name": "A. Iwobi",
              "number": 17,
              "pos": "M",
              "grid": "3:2"
            }
          },
          {
            "player": {
              "id": 18766,
              "name": "D. Calvert-Lewin",
              "number": 9,
              "pos": "F",
              "grid": "3:1"
            }
          },
          {
            "player": {
              "id": 2413,
              "name": "Richarlison",
              "number": 7,
              "pos": "F",
              "grid": "4:2"
            }
          },
          {
            "player": {
              "id": 138787,
              "name": "A. Gordon",
              "number": 24,
              "pos": "M",
              "grid": "4:1"
            }
          }
        ],
        "substitutes": [
          {
            "player": {
              "id": 18765,
              "name": "André Gomes",
              "number": 21,
              "pos": "M",
              "grid": null
            }
          },
          {
            "player": {
              "id": 18854,
              "name": "A. Townsend",
              "number": 14,
              "pos": "M",
              "grid": null
            }
          },
          {
            "player": {
              "id": 172,
              "name": "D. Alli",
              "number": 36,
              "pos": "M",
              "grid": null
            }
          },
          {
            "player": {
              "id": 2165,
              "name": "V. Mykolenko",
              "number": 19,
              "pos": "D",
              "grid": null
            }
          },
          {
            "player": {
              "id": 2461,
              "name": "S. Rondón",
              "number": 33,
              "pos": "F",
              "grid": null
            }
          },
          {
            "player": {
              "id": 17661,
              "name": "J. Branthwaite",
              "number": 32,
              "pos": "D",
              "grid": null
            }
          },
          {
            "player": {
              "id": 138417,
              "name": "N. Patterson",
              "number": 3,
              "pos": "D",
              "grid": null
            }
          },
          {
            "player": {
              "id": 19195,
              "name": "A. El Ghazi",
              "number": 34,
              "pos": "M",
              "grid": null
            }
          },
          {
            "player": {
              "id": 18858,
              "name": "A. Begović",
              "number": 15,
              "pos": "G",
              "grid": null
            }
          }
        ]
      }
    ]
  }
}