{
  "metadata": {
    "collected_at": "2025-10-10T19:41:10.700180",
    "records_count": 1,
    "api_usage": 935,
    "daily_limit": 7500
  },
  "data": {
    "fixture_info": {
      "id": 592293,
      "date": "2020-12-28T17:30:00+00:00",
      "home_team": "Chelsea",
      "away_team": "Aston Villa",
      "score": {
        "home": 1,
        "away": 1
      },
      "status": "FT"
    },
    "players": [
      {
        "team": {
          "id": 49,
          "name": "Chelsea",
          "logo": "https://media.api-sports.io/football/teams/49.png",
          "update": "2021-05-17T16:26:00+00:00"
        },
        "players": [
          {
            "player": {
              "id": 2986,
              "name": "Edouard Mendy",
              "photo": "https://media.api-sports.io/football/players/2986.png"
            },
            "statistics": [
              {
                "games": {
                  "minutes": 90,
                  "number": 16,
                  "position": "G",
                  "rating": "6.6",
                  "captain": false,
                  "substitute": false
                },
                "offsides": null,
                "shots": {
                  "total": null,
                  "on": null
                },
                "goals": {
                  "total": null,
                  "conceded": 1,
                  "assists": null,
                  "saves": 1
                },
                "passes": {
                  "total": 31,
                  "key": null,
                  "accuracy": "26"
                },
                "tackles": {
                  "total": null,
                  "blocks": null,
                  "interceptions": null
                },
                "duels": {
                  "total": 2,
                  "won": 2
                },
                "dribbles": {
                  "attempts": null,
                  "success": null,
                  "past": null
                },
                "fouls": {
                  "drawn": null,
                  "committed": null
                },
                "cards": {
                  "yellow": 0,
                  "red": 0
                },
                "penalty": {
                  "won": null,
                  "commited": null,
                  "scored": 0,
                  "missed": 0,
                  "saved": 0
                }
              }
            ]
          },
          {
            "player": {
              "id": 2280,
              "name": "César Azpilicueta",
              "photo": "https://media.api-sports.io/football/players/2280.png"
            },
            "statistics": [
              {
                "games": {
                  "minutes": 90,
                  "number": 28,
                  "position": "D",
                  "rating": "6.6",
                  "captain": true,
                  "substitute": false
                },
                "offsides": null,
                "shots": {
                  "total": null,
                  "on": null
                },
                "goals": {
                  "total": null,
                  "conceded": 0,
                  "assists": null,
                  "saves": null
                },
                "passes": {
                  "total": 57,
                  "key": 2,
                  "accuracy": "42"
                },
                "tackles": {
                  "total": 2,
                  "blocks": null,
                  "interceptions": 1
                },
                "duels": {
                  "total": 8,
                  "won": 3
                },
                "dribbles": {
                  "attempts": 1,
                  "success": null,
                  "past": null
                },
                "fouls": {
                  "drawn": 1,
                  "committed": 2
                },
                "cards": {
                  "yellow": 1,
                  "red": 0
                },
                "penalty": {
                  "won": null,
                  "commited": null,
                  "scored": 0,
                  "missed": 0,
                  "saved": null
                }
              }
            ]
          },
          {
            "player": {
              "id": 2282,
              "name": "Andreas Christensen",
              "photo": "https://media.api-sports.io/football/players/2282.png"
            },
            "statistics": [
              {
                "games": {
                  "minutes": 90,
                  "number": 4,
                  "position": "D",
                  "rating": "6.6",
                  "captain": false,
                  "substitute": false
                },
                "offsides": null,
                "shots": {
                  "total": null,
                  "on": null
                },
                "goals": {
                  "total": null,
                  "conceded": 0,
                  "assists": null,
                  "saves": null
                },
                "passes": {
                  "total": 64,
                  "key": null,
                  "accuracy": "56"
                },
                "tackles": {
                  "total": null,
                  "blocks": null,
                  "interceptions": 1
                },
                "duels": {
                  "total": 3,
                  "won": 2
                },
                "dribbles": {
                  "attempts": null,
                  "success": null,
                  "past": 1
                },
                "fouls": {
                  "drawn": null,
                  "committed": null
                },
                "cards": {
                  "yellow": 0,
                  "red": 0
                },
                "penalty": {
                  "won": null,
                  "commited": null,
                  "scored": 0,
                  "missed": 0,
                  "saved": null
                }
              }
            ]
          },
          {
            "player": {
              "id": 2285,
              "name": "Antonio Rüdiger",
              "photo": "https://media.api-sports.io/football/players/2285.png"
            },
            "statistics": [
              {
                "games": {
                  "minutes": 90,
                  "number": 2,
                  "position": "D",
                  "rating": "7.5",
                  "captain": false,
                  "substitute": false
                },
                "offsides": null,
                "shots": {
                  "total": 2,
                  "on": 1
                },
                "goals": {
                  "total": null,
                  "conceded": 0,
                  "assists": null,
                  "saves": null
                },
                "passes": {
                  "total": 66,
                  "key": null,
                  "accuracy": "57"
                },
                "tackles": {
                  "total": 1,
                  "blocks": 1,
                  "interceptions": 2
                },
                "duels": {
                  "total": 4,
                  "won": 4
                },
                "dribbles": {
                  "attempts": null,
                  "success": null,
                  "past": null
                },
                "fouls": {
                  "drawn": null,
                  "committed": null
                },
                "cards": {
                  "yellow": 0,
                  "red": 0
                },
                "penalty": {
                  "won": null,
                  "commited": null,
                  "scored": 0,
                  "missed": 0,
                  "saved": null
                }
              }
            ]
          },
          {
            "player": {
              "id": 2933,
              "name": "Ben Chilwell",
              "photo": "https://media.api-sports.io/football/players/2933.png"
            },
            "statistics": [
              {
                "games": {
                  "minutes": 90,
                  "number": 21,
                  "position": "D",
                  "rating": "6.6",
                  "captain": false,
                  "substitute": false
                },
                "offsides": null,
                "shots": {
                  "total": 1,
                  "on": null
                },
                "goals": {
                  "total": null,
                  "conceded": 0,
                  "assists": 1,
                  "saves": null
                },
                "passes": {
                  "total": 50,
                  "key": 1,
                  "accuracy": "40"
                },
                "tackles": {
                  "total": null,
                  "blocks": null,
                  "interceptions": null
                },
                "duels": {
                  "total": 6,
                  "won": 2
                },
                "dribbles": {
                  "attempts": 1,
                  "success": null,
                  "past": null
                },
                "fouls": {
                  "drawn": null,
                  "committed": 1
                },
                "cards": {
                  "yellow": 0,
                  "red": 0
                },
                "penalty": {
                  "won": null,
                  "commited": null,
                  "scored": 0,
                  "missed": 0,
                  "saved": null
                }
              }
            ]
          },
          {
            "player": {
              "id": 2290,
              "name": "N'Golo Kanté",
              "photo": "https://media.api-sports.io/football/players/2290.png"
            },
            "statistics": [
              {
                "games": {
                  "minutes": 90,
                  "number": 7,
                  "position": "M",
                  "rating": "7.7",
                  "captain": false,
                  "substitute": false
                },
                "offsides": null,
                "shots": {
                  "total": 2,
                  "on": 1
                },
                "goals": {
                  "total": null,
                  "conceded": 0,
                  "assists": null,
                  "saves": null
                },
                "passes": {
                  "total": 55,
                  "key": 3,
                  "accuracy": "44"
                },
                "tackles": {
                  "total": 5,
                  "blocks": null,
                  "interceptions": 2
                },
                "duels": {
                  "total": 15,
                  "won": 7
                },
                "dribbles": {
                  "attempts": 2,
                  "success": 2,
                  "past": 1
                },
                "fouls": {
                  "drawn": null,
                  "committed": 3
                },
                "cards": {
                  "yellow": 1,
                  "red": 0
                },
                "penalty": {
                  "won": null,
                  "commited": null,
                  "scored": 0,
                  "missed": 0,
                  "saved": null
                }
              }
            ]
          },
          {
            "player": {
              "id": 2289,
              "name": "Jorginho",
              "photo": "https://media.api-sports.io/football/players/2289.png"
            },
            "statistics": [
              {
                "games": {
                  "minutes": 72,
                  "number": 5,
                  "position": "M",
                  "rating": "7.2",
                  "captain": false,
                  "substitute": false
                },
                "offsides": null,
                "shots": {
                  "total": null,
                  "on": null
                },
                "goals": {
                  "total": null,
                  "conceded": 0,
                  "assists": null,
                  "saves": null
                },
                "passes": {
                  "total": 46,
                  "key": null,
                  "accuracy": "38"
                },
                "tackles": {
                  "total": 5,
                  "blocks": null,
                  "interceptions": 4
                },
                "duels": {
                  "total": 9,
                  "won": 5
                },
                "dribbles": {
                  "attempts": null,
                  "success": null,
                  "past": 2
                },
                "fouls": {
                  "drawn": null,
                  "committed": 2
                },
                "cards": {
                  "yellow": 0,
                  "red": 0
                },
                "penalty": {
                  "won": null,
                  "commited": null,
                  "scored": 0,
                  "missed": 0,
                  "saved": null
                }
              }
            ]
          },
          {
            "player": {
              "id": 19220,
              "name": "Mason Mount",
              "photo": "https://media.api-sports.io/football/players/19220.png"
            },
            "statistics": [
              {
                "games": {
                  "minutes": 90,
                  "number": 19,
                  "position": "M",
                  "rating": "7.2",
                  "captain": false,
                  "substitute": false
                },
                "offsides": null,
                "shots": {
                  "total": 1,
                  "on": null
                },
                "goals": {
                  "total": null,
                  "conceded": 0,
                  "assists": null,
                  "saves": null
                },
                "passes": {
                  "total": 63,
                  "key": 3,
                  "accuracy": "56"
                },
                "tackles": {
                  "total": 2,
                  "blocks": 1,
                  "interceptions": 1
                },
                "duels": {
                  "total": 13,
                  "won": 4
                },
                "dribbles": {
                  "attempts": 3,
                  "success": 1,
                  "past": null
                },
                "fouls": {
                  "drawn": null,
                  "committed": 3
                },
                "cards": {
                  "yellow": 0,
                  "red": 0
                },
                "penalty": {
                  "won": null,
                  "commited": null,
                  "scored": 0,
                  "missed": 0,
                  "saved": null
                }
              }
            ]
          },
          {
            "player": {
              "id": 2298,
              "name": "Callum Hudson-Odoi",
              "photo": "https://media.api-sports.io/football/players/2298.png"
            },
            "statistics": [
              {
                "games": {
                  "minutes": 90,
                  "number": 20,
                  "position": "F",
                  "rating": "7.2",
                  "captain": false,
                  "substitute": false
                },
                "offsides": null,
                "shots": {
                  "total": 1,
                  "on": 1
                },
                "goals": {
                  "total": null,
                  "conceded": 0,
                  "assists": null,
                  "saves": null
                },
                "passes": {
                  "total": 41,
                  "key": 2,
                  "accuracy": "32"
                },
                "tackles": {
                  "total": 2,
                  "blocks": null,
                  "interceptions": null
                },
                "duels": {
                  "total": 10,
                  "won": 4
                },
                "dribbles": {
                  "attempts": 1,
                  "success": null,
                  "past": 2
                },
                "fouls": {
                  "drawn": 2,
                  "committed": 1
                },
                "cards": {
                  "yellow": 0,
                  "red": 0
                },
                "penalty": {
                  "won": null,
                  "commited": null,
                  "scored": 0,
                  "missed": 0,
                  "saved": null
                }
              }
            ]
          },
          {
            "player": {
              "id": 2295,
              "name": "Olivier Giroud",
              "photo": "https://media.api-sports.io/football/players/2295.png"
            },
            "statistics": [
              {
                "games": {
                  "minutes": 72,
                  "number": 18,
                  "position": "F",
                  "rating": "7.3",
                  "captain": false,
                  "substitute": false
                },
                "offsides": null,
                "shots": {
                  "total": 1,
                  "on": 1
                },
                "goals": {
                  "total": 1,
                  "conceded": 0,
                  "assists": null,
                  "saves": null
                },
                "passes": {
                  "total": 20,
                  "key": null,
                  "accuracy": "13"
                },
                "tackles": {
                  "total": null,
                  "blocks": 1,
                  "interceptions": 1
                },
                "duels": {
                  "total": 13,
                  "won": 4
                },
                "dribbles": {
                  "attempts": null,
                  "success": null,
                  "past": null
                },
                "fouls": {
                  "drawn": null,
                  "committed": 1
                },
                "cards": {
                  "yellow": 1,
                  "red": 0
                },
                "penalty": {
                  "won": null,
                  "commited": null,
                  "scored": 0,
                  "missed": 0,
                  "saved": null
                }
              }
            ]
          },
          {
            "player": {
              "id": 17,
              "name": "Christian Pulišić",
              "photo": "https://media.api-sports.io/football/players/17.png"
            },
            "statistics": [
              {
                "games": {
                  "minutes": 90,
                  "number": 10,
                  "position": "F",
                  "rating": "5.9",
                  "captain": false,
                  "substitute": false
                },
                "offsides": null,
                "shots": {
                  "total": 3,
                  "on": 1
                },
                "goals": {
                  "total": null,
                  "conceded": 0,
                  "assists": null,
                  "saves": null
                },
                "passes": {
                  "total": 33,
                  "key": null,
                  "accuracy": "28"
                },
                "tackles": {
                  "total": null,
                  "blocks": null,
                  "interceptions": 1
                },
                "duels": {
                  "total": 13,
                  "won": 1
                },
                "dribbles": {
                  "attempts": 6,
                  "success": 1,
                  "past": 3
                },
                "fouls": {
                  "drawn": null,
                  "committed": 2
                },
                "cards": {
                  "yellow": 0,
                  "red": 0
                },
                "penalty": {
                  "won": null,
                  "commited": null,
                  "scored": 0,
                  "missed": 0,
                  "saved": null
                }
              }
            ]
          },
          {
            "player": {
              "id": 2273,
              "name": "Kepa Arrizabalaga",
              "photo": "https://media.api-sports.io/football/players/2273.png"
            },
            "statistics": [
              {
                "games": {
                  "minutes": null,
                  "number": 1,
                  "position": "G",
                  "rating": null,
                  "captain": false,
                  "substitute": true
                },
                "offsides": null,
                "shots": {
                  "total": null,
                  "on": null
                },
                "goals": {
                  "total": null,
                  "conceded": 0,
                  "assists": null,
                  "saves": null
                },
                "passes": {
                  "total": null,
                  "key": null,
                  "accuracy": null
                },
                "tackles": {
                  "total": null,
                  "blocks": null,
                  "interceptions": null
                },
                "duels": {
                  "total": null,
                  "won": null
                },
                "dribbles": {
                  "attempts": null,
                  "success": null,
                  "past": null
                },
                "fouls": {
                  "drawn": null,
                  "committed": null
                },
                "cards": {
                  "yellow": 0,
                  "red": 0
                },
                "penalty": {
                  "won": null,
                  "commited": null,
                  "scored": 0,
                  "missed": 0,
                  "saved": null
                }
              }
            ]
          },
          {
            "player": {
              "id": 259,
              "name": "Thiago Silva",
              "photo": "https://media.api-sports.io/football/players/259.png"
            },
            "statistics": [
              {
                "games": {
                  "minutes": null,
                  "number": 6,
                  "position": "D",
                  "rating": null,
                  "captain": false,
                  "substitute": true
                },
                "offsides": null,
                "shots": {
                  "total": null,
                  "on": null
                },
                "goals": {
                  "total": null,
                  "conceded": 0,
                  "assists": null,
                  "saves": null
                },
                "passes": {
                  "total": null,
                  "key": null,
                  "accuracy": null
                },
                "tackles": {
                  "total": null,
                  "blocks": null,
                  "interceptions": null
                },
                "duels": {
                  "total": null,
                  "won": null
                },
                "dribbles": {
                  "attempts": null,
                  "success": null,
                  "past": null
                },
                "fouls": {
                  "drawn": null,
                  "committed": null
                },
                "cards": {
                  "yellow": 0,
                  "red": 0
                },
                "penalty": {
                  "won": null,
                  "commited": null,
                  "scored": 0,
                  "missed": 0,
                  "saved": null
                }
              }
            ]
          },
          {
            "player": {
              "id": 19209,
              "name": "Fikayo Tomori",
              "photo": "https://media.api-sports.io/football/players/19209.png"
            },
            "statistics": [
              {
                "games": {
                  "minutes": null,
                  "number": 14,
                  "position": "D",
                  "rating": null,
                  "captain": false,
                  "substitute": true
                },
                "offsides": null,
                "shots": {
                  "total": null,
                  "on": null
                },
                "goals": {
                  "total": null,
                  "conceded": 0,
                  "assists": null,
                  "saves": null
                },
                "passes": {
                  "total": null,
                  "key": null,
                  "accuracy": null
                },
                "tackles": {
                  "total": null,
                  "blocks": null,
                  "interceptions": null
                },
                "duels": {
                  "total": null,
                  "won": null
                },
                "dribbles": {
                  "attempts": null,
                  "success": null,
                  "past": null
                },
                "fouls": {
                  "drawn": null,
                  "committed": null
                },
                "cards": {
                  "yellow": 0,
                  "red": 0
                },
                "penalty": {
                  "won": null,
                  "commited": null,
                  "scored": 0,
                  "missed": 0,
                  "saved": null
                }
              }
            ]
          },
          {
            "player": {
              "id": 2284,
              "name": "Emerson Palmieri",
              "photo": "https://media.api-sports.io/football/players/2284.png"
            },
            "statistics": [
              {
                "games": {
                  "minutes": null,
                  "number": 33,
                  "position": "D",
                  "rating": null,
                  "captain": false,
                  "substitute": true
                },
                "offsides": null,
                "shots": {
                  "total": null,
                  "on": null
                },
                "goals": {
                  "total": null,
                  "conceded": 0,
                  "assists": null,
                  "saves": null
                },
                "passes": {
                  "total": null,
                  "key": null,
                  "accuracy": null
                },
                "tackles": {
                  "total": null,
                  "blocks": null,
                  "interceptions": null
                },
                "duels": {
                  "total": null,
                  "won": null
                },
                "dribbles": {
                  "attempts": null,
                  "success": null,
                  "past": null
                },
                "fouls": {
                  "drawn": null,
                  "committed": null
                },
                "cards": {
                  "yellow": 0,
                  "red": 0
                },
                "penalty": {
                  "won": null,
                  "commited": null,
                  "scored": 0,
                  "missed": 0,
                  "saved": null
                }
              }
            ]
          },
          {
            "player": {
              "id": 2291,
              "name": "Mateo Kovačić",
              "photo": "https://media.api-sports.io/football/players/2291.png"
            },
            "statistics": [
              {
                "games": {
                  "minutes": null,
                  "number": 17,
                  "position": "M",
                  "rating": null,
                  "captain": false,
                  "substitute": true
                },
                "offsides": null,
                "shots": {
                  "total": null,
                  "on": null
                },
                "goals": {
                  "total": null,
                  "conceded": 0,
                  "assists": null,
                  "saves": null
                },
                "passes": {
                  "total": null,
                  "key": null,
                  "accuracy": null
                },
                "tackles": {
                  "total": null,
                  "blocks": null,
                  "interceptions": null
                },
                "duels": {
                  "total": null,
                  "won": null
                },
                "dribbles": {
                  "attempts": null,
                  "success": null,
                  "past": null
                },
                "fouls": {
                  "drawn": null,
                  "committed": null
                },
                "cards": {
                  "yellow": 0,
                  "red": 0
                },
                "penalty": {
                  "won": null,
                  "commited": null,
                  "scored": 0,
                  "missed": 0,
                  "saved": null
                }
              }
            ]
          },
          {
            "player": {
              "id": 130423,
              "name": "Billy Gilmour",
              "photo": "https://media.api-sports.io/football/players/130423.png"
            },
            "statistics": [
              {
                "games": {
                  "minutes": null,
                  "number": 23,
                  "position": "M",
                  "rating": null,
                  "captain": false,
                  "substitute": true
                },
                "offsides": null,
                "shots": {
                  "total": null,
                  "on": null
                },
                "goals": {
                  "total": null,
                  "conceded": 0,
                  "assists": null,
                  "saves": null
                },
                "passes": {
                  "total": null,
                  "key": null,
                  "accuracy": null
                },
                "tackles": {
                  "total": null,
                  "blocks": null,
                  "interceptions": null
                },
                "duels": {
                  "total": null,
                  "won": null
                },
                "dribbles": {
                  "attempts": null,
                  "success": null,
                  "past": null
                },
                "fouls": {
                  "drawn": null,
                  "committed": null
                },
                "cards": {
                  "yellow": 0,
                  "red": 0
                },
                "penalty": {
                  "won": null,
                  "commited": null,
                  "scored": 0,
                  "missed": 0,
                  "saved": null
                }
              }
            ]
          },
          {
            "player": {
              "id": 978,
              "name": "Kai Havertz",
              "photo": "https://media.api-sports.io/football/players/978.png"
            },
            "statistics": [
              {
                "games": {
                  "minutes": 18,
                  "number": 29,
                  "position": "M",
                  "rating": "6.3",
                  "captain": false,
                  "substitute": true
                },
                "offsides": null,
                "shots": {
                  "total": null,
                  "on": null
                },
                "goals": {
                  "total": null,
                  "conceded": 0,
                  "assists": null,
                  "saves": null
                },
                "passes": {
                  "total": 18,
                  "key": null,
                  "accuracy": "16"
                },
                "tackles": {
                  "total": null,
                  "blocks": null,
                  "interceptions": 1
                },
                "duels": {
                  "total": 5,
                  "won": 1
                },
                "dribbles": {
                  "attempts": null,
                  "success": null,
                  "past": 1
                },
                "fouls": {
                  "drawn": null,
                  "committed": 1
                },
                "cards": {
                  "yellow": 0,
                  "red": 0
                },
                "penalty": {
                  "won": null,
                  "commited": null,
                  "scored": 0,
                  "missed": 0,
                  "saved": null
                }
              }
            ]
          },
          {
            "player": {
              "id": 19194,
              "name": "Tammy Abraham",
              "photo": "https://media.api-sports.io/football/players/19194.png"
            },
            "statistics": [
              {
                "games": {
                  "minutes": null,
                  "number": 9,
                  "position": "F",
                  "rating": null,
                  "captain": false,
                  "substitute": true
                },
                "offsides": null,
                "shots": {
                  "total": null,
                  "on": null
                },
                "goals": {
                  "total": null,
                  "conceded": 0,
                  "assists": null,
                  "saves": null
                },
                "passes": {
                  "total": null,
                  "key": null,
                  "accuracy": null
                },
                "tackles": {
                  "total": null,
                  "blocks": null,
                  "interceptions": null
                },
                "duels": {
                  "total": null,
                  "won": null
                },
                "dribbles": {
                  "attempts": null,
                  "success": null,
                  "past": null
                },
                "fouls": {
                  "drawn": null,
                  "committed": null
                },
                "cards": {
                  "yellow": 0,
                  "red": 0
                },
                "penalty": {
                  "won": null,
                  "commited": null,
                  "scored": 0,
                  "missed": 0,
                  "saved": null
                }
              }
            ]
          },
          {
            "player": {
              "id": 1166,
              "name": "Timo Werner",
              "photo": "https://media.api-sports.io/football/players/1166.png"
            },
            "statistics": [
              {
                "games": {
                  "minutes": 18,
                  "number": 11,
                  "position": "F",
                  "rating": "6.7",
                  "captain": false,
                  "substitute": true
                },
                "offsides": null,
                "shots": {
                  "total": 1,
                  "on": null
                },
                "goals": {
                  "total": null,
                  "conceded": 0,
                  "assists": null,
                  "saves": null
                },
                "passes": {
                  "total": 6,
                  "key": null,
                  "accuracy": "6"
                },
                "tackles": {
                  "total": null,
                  "blocks": null,
                  "interceptions": null
                },
                "duels": {
                  "total": 1,
                  "won": null
                },
                "dribbles": {
                  "attempts": null,
                  "success": null,
                  "past": null
                },
                "fouls": {
                  "drawn": null,
                  "committed": null
                },
                "cards": {
                  "yellow": 0,
                  "red": 0
                },
                "penalty": {
                  "won": null,
                  "commited": null,
                  "scored": 0,
                  "missed": 0,
                  "saved": null
                }
              }
            ]
          }
        ]
      },
      {
        "team": {
          "id": 66,
          "name": "Aston Villa",
          "logo": "https://media.api-sports.io/football/teams/66.png",
          "update": "2021-05-17T16:26:00+00:00"
        },
        "players": [
          {
            "player": {
              "id": 19599,
              "name": "Emiliano Martínez",
              "photo": "https://media.api-sports.io/football/players/19599.png"
            },
            "statistics": [
              {
                "games": {
                  "minutes": 90,
                  "number": 26,
                  "position": "G",
                  "rating": "7",
                  "captain": false,
                  "substitute": false
                },
                "offsides": null,
                "shots": {
                  "total": null,
                  "on": null
                },
                "goals": {
                  "total": null,
                  "conceded": 1,
                  "assists": null,
                  "saves": 4
                },
                "passes": {
                  "total": 33,
                  "key": null,
                  "accuracy": "16"
                },
                "tackles": {
                  "total": null,
                  "blocks": null,
                  "interceptions": null
                },
                "duels": {
                  "total": 2,
                  "won": 2
                },
                "dribbles": {
                  "attempts": null,
                  "success": null,
                  "past": null
                },
                "fouls": {
                  "drawn": null,
                  "committed": null
                },
                "cards": {
                  "yellow": 0,
                  "red": 0
                },
                "penalty": {
                  "won": null,
                  "commited": null,
                  "scored": 0,
                  "missed": 0,
                  "saved": 0
                }
              }
            ]
          },
          {
            "player": {
              "id": 19298,
              "name": "Matty Cash",
              "photo": "https://media.api-sports.io/football/players/19298.png"
            },
            "statistics": [
              {
                "games": {
                  "minutes": 90,
                  "number": 2,
                  "position": "D",
                  "rating": "7.7",
                  "captain": false,
                  "substitute": false
                },
                "offsides": null,
                "shots": {
                  "total": 1,
                  "on": null
                },
                "goals": {
                  "total": null,
                  "conceded": 0,
                  "assists": 1,
                  "saves": null
                },
                "passes": {
                  "total": 18,
                  "key": 1,
                  "accuracy": "16"
                },
                "tackles": {
                  "total": 3,
                  "blocks": null,
                  "interceptions": 2
                },
                "duels": {
                  "total": 9,
                  "won": 5
                },
                "dribbles": {
                  "attempts": 1,
                  "success": null,
                  "past": 1
                },
                "fouls": {
                  "drawn": 2,
                  "committed": null
                },
                "cards": {
                  "yellow": 0,
                  "red": 0
                },
                "penalty": {
                  "won": null,
                  "commited": null,
                  "scored": 0,
                  "missed": 0,
                  "saved": null
                }
              }
            ]
          },
          {
            "player": {
              "id": 19354,
              "name": "Ezri Konsa",
              "photo": "https://media.api-sports.io/football/players/19354.png"
            },
            "statistics": [
              {
                "games": {
                  "minutes": 90,
                  "number": 4,
                  "position": "D",
                  "rating": "7.2",
                  "captain": false,
                  "substitute": false
                },
                "offsides": null,
                "shots": {
                  "total": null,
                  "on": null
                },
                "goals": {
                  "total": null,
                  "conceded": 0,
                  "assists": null,
                  "saves": null
                },
                "passes": {
                  "total": 23,
                  "key": null,
                  "accuracy": "20"
                },
                "tackles": {
                  "total": 3,
                  "blocks": null,
                  "interceptions": 1
                },
                "duels": {
                  "total": 6,
                  "won": 5
                },
                "dribbles": {
                  "attempts": null,
                  "success": null,
                  "past": null
                },
                "fouls": {
                  "drawn": 1,
                  "committed": null
                },
                "cards": {
                  "yellow": 0,
                  "red": 0
                },
                "penalty": {
                  "won": null,
                  "commited": null,
                  "scored": 0,
                  "missed": 0,
                  "saved": null
                }
              }
            ]
          },
          {
            "player": {
              "id": 19177,
              "name": "Kortney Hause",
              "photo": "https://media.api-sports.io/football/players/19177.png"
            },
            "statistics": [
              {
                "games": {
                  "minutes": 90,
                  "number": 30,
                  "position": "D",
                  "rating": "6.6",
                  "captain": false,
                  "substitute": false
                },
                "offsides": null,
                "shots": {
                  "total": 1,
                  "on": null
                },
                "goals": {
                  "total": null,
                  "conceded": 0,
                  "assists": null,
                  "saves": null
                },
                "passes": {
                  "total": 34,
                  "key": null,
                  "accuracy": "25"
                },
                "tackles": {
                  "total": 1,
                  "blocks": null,
                  "interceptions": 2
                },
                "duels": {
                  "total": 7,
                  "won": 4
                },
                "dribbles": {
                  "attempts": null,
                  "success": null,
                  "past": null
                },
                "fouls": {
                  "drawn": null,
                  "committed": null
                },
                "cards": {
                  "yellow": 0,
                  "red": 0
                },
                "penalty": {
                  "won": null,
                  "commited": null,
                  "scored": 0,
                  "missed": 0,
                  "saved": null
                }
              }
            ]
          },
          {
            "player": {
              "id": 18941,
              "name": "Matt Targett",
              "photo": "https://media.api-sports.io/football/players/18941.png"
            },
            "statistics": [
              {
                "games": {
                  "minutes": 90,
                  "number": 18,
                  "position": "D",
                  "rating": "6.9",
                  "captain": false,
                  "substitute": false
                },
                "offsides": null,
                "shots": {
                  "total": null,
                  "on": null
                },
                "goals": {
                  "total": null,
                  "conceded": 0,
                  "assists": null,
                  "saves": null
                },
                "passes": {
                  "total": 41,
                  "key": null,
                  "accuracy": "29"
                },
                "tackles": {
                  "total": 2,
                  "blocks": null,
                  "interceptions": 1
                },
                "duels": {
                  "total": 5,
                  "won": 5
                },
                "dribbles": {
                  "attempts": null,
                  "success": null,
                  "past": null
                },
                "fouls": {
                  "drawn": null,
                  "committed": null
                },
                "cards": {
                  "yellow": 0,
                  "red": 0
                },
                "penalty": {
                  "won": null,
                  "commited": null,
                  "scored": 0,
                  "missed": 0,
                  "saved": null
                }
              }
            ]
          },
          {
            "player": {
              "id": 47522,
              "name": "Douglas Luiz",
              "photo": "https://media.api-sports.io/football/players/47522.png"
            },
            "statistics": [
              {
                "games": {
                  "minutes": 90,
                  "number": 6,
                  "position": "M",
                  "rating": "6.9",
                  "captain": false,
                  "substitute": false
                },
                "offsides": null,
                "shots": {
                  "total": null,
                  "on": null
                },
                "goals": {
                  "total": null,
                  "conceded": 0,
                  "assists": null,
                  "saves": null
                },
                "passes": {
                  "total": 34,
                  "key": null,
                  "accuracy": "30"
                },
                "tackles": {
                  "total": 3,
                  "blocks": null,
                  "interceptions": 2
                },
                "duels": {
                  "total": 7,
                  "won": 5
                },
                "dribbles": {
                  "attempts": null,
                  "success": null,
                  "past": 1
                },
                "fouls": {
                  "drawn": 2,
                  "committed": null
                },
                "cards": {
                  "yellow": 0,
                  "red": 0
                },
                "penalty": {
                  "won": null,
                  "commited": null,
                  "scored": 0,
                  "missed": 0,
                  "saved": null
                }
              }
            ]
          },
          {
            "player": {
              "id": 19191,
              "name": "John McGinn",
              "photo": "https://media.api-sports.io/football/players/19191.png"
            },
            "statistics": [
              {
                "games": {
                  "minutes": 90,
                  "number": 7,
                  "position": "M",
                  "rating": "7.5",
                  "captain": false,
                  "substitute": false
                },
                "offsides": null,
                "shots": {
                  "total": 1,
                  "on": null
                },
                "goals": {
                  "total": null,
                  "conceded": 0,
                  "assists": null,
                  "saves": null
                },
                "passes": {
                  "total": 30,
                  "key": 2,
                  "accuracy": "23"
                },
                "tackles": {
                  "total": 3,
                  "blocks": null,
                  "interceptions": 1
                },
                "duels": {
                  "total": 19,
                  "won": 13
                },
                "dribbles": {
                  "attempts": 4,
                  "success": 2,
                  "past": 2
                },
                "fouls": {
                  "drawn": 6,
                  "committed": null
                },
                "cards": {
                  "yellow": 0,
                  "red": 0
                },
                "penalty": {
                  "won": null,
                  "commited": null,
                  "scored": 0,
                  "missed": 0,
                  "saved": null
                }
              }
            ]
          },
          {
            "player": {
              "id": 671,
              "name": "Bertrand Traoré",
              "photo": "https://media.api-sports.io/football/players/671.png"
            },
            "statistics": [
              {
                "games": {
                  "minutes": 87,
                  "number": 15,
                  "position": "M",
                  "rating": "6.9",
                  "captain": false,
                  "substitute": false
                },
                "offsides": null,
                "shots": {
                  "total": null,
                  "on": null
                },
                "goals": {
                  "total": null,
                  "conceded": 0,
                  "assists": null,
                  "saves": null
                },
                "passes": {
                  "total": 25,
                  "key": null,
                  "accuracy": "15"
                },
                "tackles": {
                  "total": 1,
                  "blocks": null,
                  "interceptions": 1
                },
                "duels": {
                  "total": 9,
                  "won": 6
                },
                "dribbles": {
                  "attempts": 3,
                  "success": 3,
                  "past": null
                },
                "fouls": {
                  "drawn": null,
                  "committed": 1
                },
                "cards": {
                  "yellow": 0,
                  "red": 0
                },
                "penalty": {
                  "won": null,
                  "commited": null,
                  "scored": 0,
                  "missed": 0,
                  "saved": null
                }
              }
            ]
          },
          {
            "player": {
              "id": 19187,
              "name": "Jack Grealish",
              "photo": "https://media.api-sports.io/football/players/19187.png"
            },
            "statistics": [
              {
                "games": {
                  "minutes": 90,
                  "number": 10,
                  "position": "M",
                  "rating": "7",
                  "captain": true,
                  "substitute": false
                },
                "offsides": null,
                "shots": {
                  "total": 1,
                  "on": 1
                },
                "goals": {
                  "total": null,
                  "conceded": 0,
                  "assists": null,
                  "saves": null
                },
                "passes": {
                  "total": 36,
                  "key": 2,
                  "accuracy": "23"
                },
                "tackles": {
                  "total": 1,
                  "blocks": null,
                  "interceptions": 1
                },
                "duels": {
                  "total": 16,
                  "won": 10
                },
                "dribbles": {
                  "attempts": 5,
                  "success": 4,
                  "past": null
                },
                "fouls": {
                  "drawn": 4,
                  "committed": 2
                },
                "cards": {
                  "yellow": 0,
                  "red": 0
                },
                "penalty": {
                  "won": null,
                  "commited": null,
                  "scored": 0,
                  "missed": 0,
                  "saved": null
                }
              }
            ]
          },
          {
            "player": {
              "id": 19195,
              "name": "Anwar El Ghazi",
              "photo": "https://media.api-sports.io/football/players/19195.png"
            },
            "statistics": [
              {
                "games": {
                  "minutes": 81,
                  "number": 21,
                  "position": "M",
                  "rating": "7.2",
                  "captain": false,
                  "substitute": false
                },
                "offsides": null,
                "shots": {
                  "total": 1,
                  "on": 1
                },
                "goals": {
                  "total": 1,
                  "conceded": 0,
                  "assists": null,
                  "saves": null
                },
                "passes": {
                  "total": 16,
                  "key": 2,
                  "accuracy": "11"
                },
                "tackles": {
                  "total": 1,
                  "blocks": null,
                  "interceptions": 2
                },
                "duels": {
                  "total": 9,
                  "won": 4
                },
                "dribbles": {
                  "attempts": 3,
                  "success": 1,
                  "past": null
                },
                "fouls": {
                  "drawn": 1,
                  "committed": null
                },
                "cards": {
                  "yellow": 1,
                  "red": 0
                },
                "penalty": {
                  "won": null,
                  "commited": null,
                  "scored": 0,
                  "missed": 0,
                  "saved": null
                }
              }
            ]
          },
          {
            "player": {
              "id": 19366,
              "name": "Ollie Watkins",
              "photo": "https://media.api-sports.io/football/players/19366.png"
            },
            "statistics": [
              {
                "games": {
                  "minutes": 90,
                  "number": 11,
                  "position": "F",
                  "rating": "6.9",
                  "captain": false,
                  "substitute": false
                },
                "offsides": null,
                "shots": {
                  "total": 1,
                  "on": null
                },
                "goals": {
                  "total": null,
                  "conceded": 0,
                  "assists": null,
                  "saves": null
                },
                "passes": {
                  "total": 21,
                  "key": 2,
                  "accuracy": "16"
                },
                "tackles": {
                  "total": 1,
                  "blocks": null,
                  "interceptions": null
                },
                "duels": {
                  "total": 11,
                  "won": 4
                },
                "dribbles": {
                  "attempts": 1,
                  "success": null,
                  "past": null
                },
                "fouls": {
                  "drawn": null,
                  "committed": null
                },
                "cards": {
                  "yellow": 0,
                  "red": 0
                },
                "penalty": {
                  "won": null,
                  "commited": null,
                  "scored": 0,
                  "missed": 0,
                  "saved": null
                }
              }
            ]
          },
          {
            "player": {
              "id": 2931,
              "name": "Tom Heaton",
              "photo": "https://media.api-sports.io/football/players/2931.png"
            },
            "statistics": [
              {
                "games": {
                  "minutes": null,
                  "number": 1,
                  "position": "G",
                  "rating": null,
                  "captain": false,
                  "substitute": true
                },
                "offsides": null,
                "shots": {
                  "total": null,
                  "on": null
                },
                "goals": {
                  "total": null,
                  "conceded": 0,
                  "assists": null,
                  "saves": null
                },
                "passes": {
                  "total": null,
                  "key": null,
                  "accuracy": null
                },
                "tackles": {
                  "total": null,
                  "blocks": null,
                  "interceptions": null
                },
                "duels": {
                  "total": null,
                  "won": null
                },
                "dribbles": {
                  "attempts": null,
                  "success": null,
                  "past": null
                },
                "fouls": {
                  "drawn": null,
                  "committed": null
                },
                "cards": {
                  "yellow": 0,
                  "red": 0
                },
                "penalty": {
                  "won": null,
                  "commited": null,
                  "scored": 0,
                  "missed": 0,
                  "saved": null
                }
              }
            ]
          },
          {
            "player": {
              "id": 21636,
              "name": "Frédéric Guilbert",
              "photo": "https://media.api-sports.io/football/players/21636.png"
            },
            "statistics": [
              {
                "games": {
                  "minutes": null,
                  "number": 24,
                  "position": "D",
                  "rating": null,
                  "captain": false,
                  "substitute": true
                },
                "offsides": null,
                "shots": {
                  "total": null,
                  "on": null
                },
                "goals": {
                  "total": null,
                  "conceded": 0,
                  "assists": null,
                  "saves": null
                },
                "passes": {
                  "total": null,
                  "key": null,
                  "accuracy": null
                },
                "tackles": {
                  "total": null,
                  "blocks": null,
                  "interceptions": null
                },
                "duels": {
                  "total": null,
                  "won": null
                },
                "dribbles": {
                  "attempts": null,
                  "success": null,
                  "past": null
                },
                "fouls": {
                  "drawn": null,
                  "committed": null
                },
                "cards": {
                  "yellow": 0,
                  "red": 0
                },
                "penalty": {
                  "won": null,
                  "commited": null,
                  "scored": 0,
                  "missed": 0,
                  "saved": null
                }
              }
            ]
          },
          {
            "player": {
              "id": 21999,
              "name": "Björn Engels",
              "photo": "https://media.api-sports.io/football/players/21999.png"
            },
            "statistics": [
              {
                "games": {
                  "minutes": null,
                  "number": 22,
                  "position": "D",
                  "rating": null,
                  "captain": false,
                  "substitute": true
                },
                "offsides": null,
                "shots": {
                  "total": null,
                  "on": null
                },
                "goals": {
                  "total": null,
                  "conceded": 0,
                  "assists": null,
                  "saves": null
                },
                "passes": {
                  "total": null,
                  "key": null,
                  "accuracy": null
                },
                "tackles": {
                  "total": null,
                  "blocks": null,
                  "interceptions": null
                },
                "duels": {
                  "total": null,
                  "won": null
                },
                "dribbles": {
                  "attempts": null,
                  "success": null,
                  "past": null
                },
                "fouls": {
                  "drawn": null,
                  "committed": null
                },
                "cards": {
                  "yellow": 0,
                  "red": 0
                },
                "penalty": {
                  "won": null,
                  "commited": null,
                  "scored": 0,
                  "missed": 0,
                  "saved": null
                }
              }
            ]
          },
          {
            "player": {
              "id": 19186,
              "name": "Ahmed El-Mohamady",
              "photo": "https://media.api-sports.io/football/players/19186.png"
            },
            "statistics": [
              {
                "games": {
                  "minutes": null,
                  "number": 27,
                  "position": "D",
                  "rating": null,
                  "captain": false,
                  "substitute": true
                },
                "offsides": null,
                "shots": {
                  "total": null,
                  "on": null
                },
                "goals": {
                  "total": null,
                  "conceded": 0,
                  "assists": null,
                  "saves": null
                },
                "passes": {
                  "total": null,
                  "key": null,
                  "accuracy": null
                },
                "tackles": {
                  "total": null,
                  "blocks": null,
                  "interceptions": null
                },
                "duels": {
                  "total": null,
                  "won": null
                },
                "dribbles": {
                  "attempts": null,
                  "success": null,
                  "past": null
                },
                "fouls": {
                  "drawn": null,
                  "committed": null
                },
                "cards": {
                  "yellow": 0,
                  "red": 0
                },
                "penalty": {
                  "won": null,
                  "commited": null,
                  "scored": 0,
                  "missed": 0,
                  "saved": null
                }
              }
            ]
          },
          {
            "player": {
              "id": 19181,
              "name": "Neil Taylor",
              "photo": "https://media.api-sports.io/football/players/19181.png"
            },
            "statistics": [
              {
                "games": {
                  "minutes": null,
                  "number": 3,
                  "position": "D",
                  "rating": null,
                  "captain": false,
                  "substitute": true
                },
                "offsides": null,
                "shots": {
                  "total": null,
                  "on": null
                },
                "goals": {
                  "total": null,
                  "conceded": 0,
                  "assists": null,
                  "saves": null
                },
                "passes": {
                  "total": null,
                  "key": null,
                  "accuracy": null
                },
                "tackles": {
                  "total": null,
                  "blocks": null,
                  "interceptions": null
                },
                "duels": {
                  "total": null,
                  "won": null
                },
                "dribbles": {
                  "attempts": null,
                  "success": null,
                  "past": null
                },
                "fouls": {
                  "drawn": null,
                  "committed": null
                },
                "cards": {
                  "yellow": 0,
                  "red": 0
                },
                "penalty": {
                  "won": null,
                  "commited": null,
                  "scored": 0,
                  "missed": 0,
                  "saved": null
                }
              }
            ]
          },
          {
            "player": {
              "id": 76,
              "name": "Marvelous Nakamba",
              "photo": "https://media.api-sports.io/football/players/76.png"
            },
            "statistics": [
              {
                "games": {
                  "minutes": null,
                  "number": 19,
                  "position": "M",
                  "rating": null,
                  "captain": false,
                  "substitute": true
                },
                "offsides": null,
                "shots": {
                  "total": null,
                  "on": null
                },
                "goals": {
                  "total": null,
                  "conceded": 0,
                  "assists": null,
                  "saves": null
                },
                "passes": {
                  "total": null,
                  "key": null,
                  "accuracy": null
                },
                "tackles": {
                  "total": null,
                  "blocks": null,
                  "interceptions": null
                },
                "duels": {
                  "total": null,
                  "won": null
                },
                "dribbles": {
                  "attempts": null,
                  "success": null,
                  "past": null
                },
                "fouls": {
                  "drawn": null,
                  "committed": null
                },
                "cards": {
                  "yellow": 0,
                  "red": 0
                },
                "penalty": {
                  "won": null,
                  "commited": null,
                  "scored": 0,
                  "missed": 0,
                  "saved": null
                }
              }
            ]
          },
          {
            "player": {
              "id": 19192,
              "name": "Jacob Ramsey",
              "photo": "https://media.api-sports.io/football/players/19192.png"
            },
            "statistics": [
              {
                "games": {
                  "minutes": 9,
                  "number": 41,
                  "position": "M",
                  "rating": "6.7",
                  "captain": false,
                  "substitute": true
                },
                "offsides": null,
                "shots": {
                  "total": 1,
                  "on": null
                },
                "goals": {
                  "total": null,
                  "conceded": 0,
                  "assists": null,
                  "saves": null
                },
                "passes": {
                  "total": 1,
                  "key": null,
                  "accuracy": "1"
                },
                "tackles": {
                  "total": null,
                  "blocks": null,
                  "interceptions": null
                },
                "duels": {
                  "total": null,
                  "won": null
                },
                "dribbles": {
                  "attempts": null,
                  "success": null,
                  "past": null
                },
                "fouls": {
                  "drawn": null,
                  "committed": null
                },
                "cards": {
                  "yellow": 0,
                  "red": 0
                },
                "penalty": {
                  "won": null,
                  "commited": null,
                  "scored": 0,
                  "missed": 0,
                  "saved": null
                }
              }
            ]
          },
          {
            "player": {
              "id": 19188,
              "name": "Conor Hourihane",
              "photo": "https://media.api-sports.io/football/players/19188.png"
            },
            "statistics": [
              {
                "games": {
                  "minutes": null,
                  "number": 14,
                  "position": "M",
                  "rating": null,
                  "captain": false,
                  "substitute": true
                },
                "offsides": null,
                "shots": {
                  "total": null,
                  "on": null
                },
                "goals": {
                  "total": null,
                  "conceded": 0,
                  "assists": null,
                  "saves": null
                },
                "passes": {
                  "total": null,
                  "key": null,
                  "accuracy": null
                },
                "tackles": {
                  "total": null,
                  "blocks": null,
                  "interceptions": null
                },
                "duels": {
                  "total": null,
                  "won": null
                },
                "dribbles": {
                  "attempts": null,
                  "success": null,
                  "past": null
                },
                "fouls": {
                  "drawn": null,
                  "committed": null
                },
                "cards": {
                  "yellow": 0,
                  "red": 0
                },
                "penalty": {
                  "won": null,
                  "commited": null,
                  "scored": 0,
                  "missed": 0,
                  "saved": null
                }
              }
            ]
          },
          {
            "player": {
              "id": 19185,
              "name": "Keinan Davis",
              "photo": "https://media.api-sports.io/football/players/19185.png"
            },
            "statistics": [
              {
                "games": {
                  "minutes": 8,
                  "number": 39,
                  "position": "F",
                  "rating": "6.3",
                  "captain": false,
                  "substitute": true
                },
                "offsides": null,
                "shots": {
                  "total": null,
                  "on": null
                },
                "goals": {
                  "total": null,
                  "conceded": 0,
                  "assists": null,
                  "saves": null
                },
                "passes": {
                  "total": 2,
                  "key": null,
                  "accuracy": "1"
                },
                "tackles": {
                  "total": null,
                  "blocks": null,
                  "interceptions": null
                },
                "duels": {
                  "total": 2,
                  "won": null
                },
                "dribbles": {
                  "attempts": null,
                  "success": null,
                  "past": null
                },
                "fouls": {
                  "drawn": null,
                  "committed": null
                },
                "cards": {
                  "yellow": 0,
                  "red": 0
                },
                "penalty": {
                  "won": null,
                  "commited": null,
                  "scored": 0,
                  "missed": 0,
                  "saved": null
                }
              }
            ]
          }
        ]
      }
    ]
  }
}