{
  "metadata": {
    "collected_at": "2025-10-01T22:21:00.289615",
    "records_count": 1,
    "api_usage": 1363,
    "daily_limit": 7500
  },
  "data": {
    "fixture_info": {
      "id": 710680,
      "date": "2021-11-28T16:30:00+00:00",
      "home_team": "Chelsea",
      "away_team": "Manchester United",
      "score": {
        "home": 1,
        "away": 1
      }
    },
    "events": [
      {
        "time": {
          "elapsed": 45,
          "extra": null
        },
        "team": {
          "id": 33,
          "name": "Manchester United",
          "logo": "https://media.api-sports.io/football/teams/33.png"
        },
        "player": {
          "id": 903,
          "name": "Scott McTominay"
        },
        "assist": {
          "id": null,
          "name": null
        },
        "type": "Card",
        "detail": "Yellow Card",
        "comments": "Foul"
      },
      {
        "time": {
          "elapsed": 49,
          "extra": null
        },
        "team": {
          "id": 33,
          "name": "Manchester United",
          "logo": "https://media.api-sports.io/football/teams/33.png"
        },
        "player": {
          "id": 909,
          "name": "Marcus Rashford"
        },
        "assist": {
          "id": null,
          "name": null
        },
        "type": "Card",
        "detail": "Yellow Card",
        "comments": "Foul"
      },
      {
        "time": {
          "elapsed": 50,
          "extra": null
        },
        "team": {
          "id": 33,
          "name": "Manchester United",
          "logo": "https://media.api-sports.io/football/teams/33.png"
        },
        "player": {
          "id": 18,
          "name": "J. Sancho"
        },
        "assist": {
          "id": null,
          "name": null
        },
        "type": "Goal",
        "detail": "Normal Goal",
        "comments": null
      },
      {
        "time": {
          "elapsed": 53,
          "extra": null
        },
        "team": {
          "id": 49,
          "name": "Chelsea",
          "logo": "https://media.api-sports.io/football/teams/49.png"
        },
        "player": {
          "id": 19545,
          "name": "Reece James"
        },
        "assist": {
          "id": null,
          "name": null
        },
        "type": "Card",
        "detail": "Yellow Card",
        "comments": "Foul"
      },
      {
        "time": {
          "elapsed": 64,
          "extra": null
        },
        "team": {
          "id": 33,
          "name": "Manchester United",
          "logo": "https://media.api-sports.io/football/teams/33.png"
        },
        "player": {
          "id": 18,
          "name": "J. Sancho"
        },
        "assist": {
          "id": 874,
          "name": "Cristiano Ronaldo"
        },
        "type": "subst",
        "detail": "Substitution 1",
        "comments": null
      },
      {
        "time": {
          "elapsed": 69,
          "extra": null
        },
        "team": {
          "id": 49,
          "name": "Chelsea",
          "logo": "https://media.api-sports.io/football/teams/49.png"
        },
        "player": {
          "id": 2289,
          "name": "Jorginho"
        },
        "assist": {
          "id": null,
          "name": null
        },
        "type": "Goal",
        "detail": "Penalty",
        "comments": null
      },
      {
        "time": {
          "elapsed": 77,
          "extra": null
        },
        "team": {
          "id": 33,
          "name": "Manchester United",
          "logo": "https://media.api-sports.io/football/teams/33.png"
        },
        "player": {
          "id": 1485,
          "name": "Bruno Fernandes"
        },
        "assist": {
          "id": null,
          "name": null
        },
        "type": "Card",
        "detail": "Yellow Card",
        "comments": "Foul"
      },
      {
        "time": {
          "elapsed": 77,
          "extra": null
        },
        "team": {
          "id": 33,
          "name": "Manchester United",
          "logo": "https://media.api-sports.io/football/teams/33.png"
        },
        "player": {
          "id": 909,
          "name": "M. Rashford"
        },
        "assist": {
          "id": 900,
          "name": "J. Lingard"
        },
        "type": "subst",
        "detail": "Substitution 2",
        "comments": null
      },
      {
        "time": {
          "elapsed": 78,
          "extra": null
        },
        "team": {
          "id": 49,
          "name": "Chelsea",
          "logo": "https://media.api-sports.io/football/teams/49.png"
        },
        "player": {
          "id": 2298,
          "name": "C. Hudson-Odoi"
        },
        "assist": {
          "id": 17,
          "name": "C. Pulisic"
        },
        "type": "subst",
        "detail": "Substitution 1",
        "comments": null
      },
      {
        "time": {
          "elapsed": 78,
          "extra": null
        },
        "team": {
          "id": 49,
          "name": "Chelsea",
          "logo": "https://media.api-sports.io/football/teams/49.png"
        },
        "player": {
          "id": 2278,
          "name": "Marcos Alonso"
        },
        "assist": {
          "id": 19220,
          "name": "M. Mount"
        },
        "type": "subst",
        "detail": "Substitution 2",
        "comments": null
      },
      {
        "time": {
          "elapsed": 82,
          "extra": null
        },
        "team": {
          "id": 49,
          "name": "Chelsea",
          "logo": "https://media.api-sports.io/football/teams/49.png"
        },
        "player": {
          "id": 1166,
          "name": "T. Werner"
        },
        "assist": {
          "id": 907,
          "name": "R. Lukaku"
        },
        "type": "subst",
        "detail": "Substitution 3",
        "comments": null
      },
      {
        "time": {
          "elapsed": 89,
          "extra": null
        },
        "team": {
          "id": 33,
          "name": "Manchester United",
          "logo": "https://media.api-sports.io/football/teams/33.png"
        },
        "player": {
          "id": 1485,
          "name": "Bruno Fernandes"
        },
        "assist": {
          "id": 547,
          "name": "D. van de Beek"
        },
        "type": "subst",
        "detail": "Substitution 3",
        "comments": null
      },
      {
        "time": {
          "elapsed": 90,
          "extra": 5
        },
        "team": {
          "id": 49,
          "name": "Chelsea",
          "logo": "https://media.api-sports.io/football/teams/49.png"
        },
        "player": {
          "id": 2289,
          "name": "Jorginho"
        },
        "assist": {
          "id": null,
          "name": null
        },
        "type": "Card",
        "detail": "Yellow Card",
        "comments": "Foul"
      },
      {
        "time": {
          "elapsed": 90,
          "extra": 6
        },
        "team": {
          "id": 33,
          "name": "Manchester United",
          "logo": "https://media.api-sports.io/football/teams/33.png"
        },
        "player": {
          "id": 885,
          "name": "Eric Bailly"
        },
        "assist": {
          "id": null,
          "name": null
        },
        "type": "Card",
        "detail": "Yellow Card",
        "comments": "Time wasting"
      },
      {
        "time": {
          "elapsed": 90,
          "extra": 2
        },
        "team": {
          "id": 33,
          "name": "Manchester United",
          "logo": "https://media.api-sports.io/football/teams/33.png"
        },
        "player": {
          "id": 874,
          "name": "Cristiano Ronaldo"
        },
        "assist": {
          "id": null,
          "name": null
        },
        "type": "Card",
        "detail": "Yellow Card",
        "comments": "Argument"
      }
    ]
  }
}