{
  "metadata": {
    "collected_at": "2025-10-01T22:27:00.882095",
    "records_count": 1,
    "api_usage": 3767,
    "daily_limit": 7500
  },
  "data": {
    "fixture_info": {
      "id": 1208276,
      "date": "2025-02-22T12:30:00+00:00",
      "home_team": "Everton",
      "away_team": "Manchester United",
      "score": {
        "home": 2,
        "away": 2
      }
    },
    "events": [
      {
        "time": {
          "elapsed": 19,
          "extra": null
        },
        "team": {
          "id": 45,
          "name": "Everton",
          "logo": "https://media.api-sports.io/football/teams/45.png"
        },
        "player": {
          "id": 125743,
          "name": "Beto"
        },
        "assist": {
          "id": 18805,
          "name": "A. Doucouré"
        },
        "type": "Goal",
        "detail": "Normal Goal",
        "comments": null
      },
      {
        "time": {
          "elapsed": 33,
          "extra": null
        },
        "team": {
          "id": 45,
          "name": "Everton",
          "logo": "https://media.api-sports.io/football/teams/45.png"
        },
        "player": {
          "id": 18805,
          "name": "A. Doucouré"
        },
        "assist": {
          "id": null,
          "name": null
        },
        "type": "Goal",
        "detail": "Normal Goal",
        "comments": null
      },
      {
        "time": {
          "elapsed": 45,
          "extra": 3
        },
        "team": {
          "id": 45,
          "name": "Everton",
          "logo": "https://media.api-sports.io/football/teams/45.png"
        },
        "player": {
          "id": 270139,
          "name": "Jake O'Brien"
        },
        "assist": {
          "id": null,
          "name": null
        },
        "type": "Card",
        "detail": "Yellow Card",
        "comments": "Foul"
      },
      {
        "time": {
          "elapsed": 54,
          "extra": null
        },
        "team": {
          "id": 45,
          "name": "Everton",
          "logo": "https://media.api-sports.io/football/teams/45.png"
        },
        "player": {
          "id": 15884,
          "name": "J. Lindstrøm"
        },
        "assist": {
          "id": 894,
          "name": "A. Young"
        },
        "type": "subst",
        "detail": "Substitution 1",
        "comments": null
      },
      {
        "time": {
          "elapsed": 62,
          "extra": null
        },
        "team": {
          "id": 33,
          "name": "Manchester United",
          "logo": "https://media.api-sports.io/football/teams/33.png"
        },
        "player": {
          "id": 747,
          "name": "Casemiro"
        },
        "assist": {
          "id": 284324,
          "name": "A. Garnacho"
        },
        "type": "subst",
        "detail": "Substitution 1",
        "comments": null
      },
      {
        "time": {
          "elapsed": 63,
          "extra": null
        },
        "team": {
          "id": 45,
          "name": "Everton",
          "logo": "https://media.api-sports.io/football/teams/45.png"
        },
        "player": {
          "id": 895,
          "name": "James Garner"
        },
        "assist": {
          "id": null,
          "name": null
        },
        "type": "Card",
        "detail": "Yellow Card",
        "comments": "Foul"
      },
      {
        "time": {
          "elapsed": 70,
          "extra": null
        },
        "team": {
          "id": 33,
          "name": "Manchester United",
          "logo": "https://media.api-sports.io/football/teams/33.png"
        },
        "player": {
          "id": 545,
          "name": "N. Mazraoui"
        },
        "assist": {
          "id": 342970,
          "name": "L. Yoro"
        },
        "type": "subst",
        "detail": "Substitution 2",
        "comments": null
      },
      {
        "time": {
          "elapsed": 70,
          "extra": null
        },
        "team": {
          "id": 33,
          "name": "Manchester United",
          "logo": "https://media.api-sports.io/football/teams/33.png"
        },
        "player": {
          "id": 288006,
          "name": "R. Højlund"
        },
        "assist": {
          "id": 389309,
          "name": "C. Obi"
        },
        "type": "subst",
        "detail": "Substitution 3",
        "comments": null
      },
      {
        "time": {
          "elapsed": 72,
          "extra": null
        },
        "team": {
          "id": 33,
          "name": "Manchester United",
          "logo": "https://media.api-sports.io/football/teams/33.png"
        },
        "player": {
          "id": 1485,
          "name": "Bruno Fernandes"
        },
        "assist": {
          "id": null,
          "name": null
        },
        "type": "Goal",
        "detail": "Normal Goal",
        "comments": null
      },
      {
        "time": {
          "elapsed": 79,
          "extra": null
        },
        "team": {
          "id": 45,
          "name": "Everton",
          "logo": "https://media.api-sports.io/football/teams/45.png"
        },
        "player": {
          "id": 894,
          "name": "Ashley Young"
        },
        "assist": {
          "id": null,
          "name": null
        },
        "type": "Card",
        "detail": "Yellow Card",
        "comments": "Foul"
      },
      {
        "time": {
          "elapsed": 80,
          "extra": null
        },
        "team": {
          "id": 33,
          "name": "Manchester United",
          "logo": "https://media.api-sports.io/football/teams/33.png"
        },
        "player": {
          "id": 51494,
          "name": "M. Ugarte"
        },
        "assist": {
          "id": null,
          "name": null
        },
        "type": "Goal",
        "detail": "Normal Goal",
        "comments": null
      },
      {
        "time": {
          "elapsed": 81,
          "extra": null
        },
        "team": {
          "id": 45,
          "name": "Everton",
          "logo": "https://media.api-sports.io/football/teams/45.png"
        },
        "player": {
          "id": 895,
          "name": "J. Garner"
        },
        "assist": {
          "id": 284500,
          "name": "T. Iroegbunam"
        },
        "type": "subst",
        "detail": "Substitution 2",
        "comments": null
      },
      {
        "time": {
          "elapsed": 81,
          "extra": null
        },
        "team": {
          "id": 45,
          "name": "Everton",
          "logo": "https://media.api-sports.io/football/teams/45.png"
        },
        "player": {
          "id": 18805,
          "name": "A. Doucouré"
        },
        "assist": {
          "id": 195993,
          "name": "C. Alcaraz"
        },
        "type": "subst",
        "detail": "Substitution 3",
        "comments": null
      },
      {
        "time": {
          "elapsed": 90,
          "extra": 9
        },
        "team": {
          "id": 45,
          "name": "Everton",
          "logo": "https://media.api-sports.io/football/teams/45.png"
        },
        "player": {
          "id": 2990,
          "name": "Idrissa Gueye"
        },
        "assist": {
          "id": null,
          "name": null
        },
        "type": "Card",
        "detail": "Yellow Card",
        "comments": "Argument"
      },
      {
        "time": {
          "elapsed": 90,
          "extra": 5
        },
        "team": {
          "id": 45,
          "name": "Everton",
          "logo": "https://media.api-sports.io/football/teams/45.png"
        },
        "player": {
          "id": 894,
          "name": "Ashley Young"
        },
        "assist": {
          "id": null,
          "name": null
        },
        "type": "Var",
        "detail": "Penalty cancelled",
        "comments": null
      },
      {
        "time": {
          "elapsed": 90,
          "extra": null
        },
        "team": {
          "id": 33,
          "name": "Manchester United",
          "logo": "https://media.api-sports.io/football/teams/33.png"
        },
        "player": {
          "id": 389309,
          "name": "Chido Obi-Martin"
        },
        "assist": {
          "id": null,
          "name": null
        },
        "type": "Card",
        "detail": "Yellow Card",
        "comments": null
      }
    ]
  }
}