{
  "metadata": {
    "collected_at": "2025-10-10T19:39:15.177524",
    "records_count": 1,
    "api_usage": 61,
    "daily_limit": 7500
  },
  "data": {
    "fixture_info": {
      "id": 592153,
      "date": "2020-09-20T15:30:00+00:00",
      "home_team": "Chelsea",
      "away_team": "Liverpool",
      "score": {
        "home": 0,
        "away": 2
      },
      "status": "FT"
    },
    "lineups": [
      {
        "team": {
          "id": 49,
          "name": "Chelsea",
          "logo": "https://media.api-sports.io/football/teams/49.png",
          "colors": null
        },
        "coach": {
          "id": 20,
          "name": "F. Lampard",
          "photo": "https://media.api-sports.io/football/coachs/20.png"
        },
        "formation": "4-3-3",
        "startXI": [
          {
            "player": {
              "id": 2273,
              "name": "Kepa",
              "number": 1,
              "pos": "G",
              "grid": "1:1"
            }
          },
          {
            "player": {
              "id": 2278,
              "name": "Marcos Alonso",
              "number": 3,
              "pos": "D",
              "grid": "2:4"
            }
          },
          {
            "player": {
              "id": 2726,
              "name": "K. Zouma",
              "number": 15,
              "pos": "D",
              "grid": "2:3"
            }
          },
          {
            "player": {
              "id": 2282,
              "name": "A. Christensen",
              "number": 4,
              "pos": "D",
              "grid": "2:2"
            }
          },
          {
            "player": {
              "id": 19545,
              "name": "R. James",
              "number": 24,
              "pos": "D",
              "grid": "2:1"
            }
          },
          {
            "player": {
              "id": 2291,
              "name": "M. Kovačić",
              "number": 17,
              "pos": "M",
              "grid": "3:3"
            }
          },
          {
            "player": {
              "id": 2289,
              "name": "Jorginho",
              "number": 5,
              "pos": "M",
              "grid": "3:2"
            }
          },
          {
            "player": {
              "id": 2290,
              "name": "N. Kanté",
              "number": 7,
              "pos": "M",
              "grid": "3:1"
            }
          },
          {
            "player": {
              "id": 19220,
              "name": "M. Mount",
              "number": 19,
              "pos": "F",
              "grid": "4:3"
            }
          },
          {
            "player": {
              "id": 978,
              "name": "K. Havertz",
              "number": 29,
              "pos": "F",
              "grid": "4:2"
            }
          },
          {
            "player": {
              "id": 1166,
              "name": "T. Werner",
              "number": 11,
              "pos": "F",
              "grid": "4:1"
            }
          }
        ],
        "substitutes": [
          {
            "player": {
              "id": 19209,
              "name": "F. Tomori",
              "number": 14,
              "pos": "D",
              "grid": null
            }
          },
          {
            "player": {
              "id": 2287,
              "name": "R. Barkley",
              "number": 8,
              "pos": "M",
              "grid": null
            }
          },
          {
            "player": {
              "id": 19194,
              "name": "T. Abraham",
              "number": 9,
              "pos": "F",
              "grid": null
            }
          },
          {
            "player": {
              "id": 2275,
              "name": "W. Caballero",
              "number": 13,
              "pos": "G",
              "grid": null
            }
          },
          {
            "player": {
              "id": 2298,
              "name": "C. Hudson-Odoi",
              "number": 20,
              "pos": "F",
              "grid": null
            }
          },
          {
            "player": {
              "id": 2280,
              "name": "Azpilicueta",
              "number": 28,
              "pos": "D",
              "grid": null
            }
          },
          {
            "player": {
              "id": 2295,
              "name": "O. Giroud",
              "number": 18,
              "pos": "F",
              "grid": null
            }
          }
        ]
      },
      {
        "team": {
          "id": 40,
          "name": "Liverpool",
          "logo": "https://media.api-sports.io/football/teams/40.png",
          "colors": null
        },
        "coach": {
          "id": 1,
          "name": "J. Klopp",
          "photo": "https://media.api-sports.io/football/coachs/1.png"
        },
        "formation": "4-3-3",
        "startXI": [
          {
            "player": {
              "id": 280,
              "name": "Alisson",
              "number": 1,
              "pos": "G",
              "grid": "1:1"
            }
          },
          {
            "player": {
              "id": 290,
              "name": "V. van Dijk",
              "number": 4,
              "pos": "D",
              "grid": "2:4"
            }
          },
          {
            "player": {
              "id": 289,
              "name": "A. Robertson",
              "number": 26,
              "pos": "D",
              "grid": "2:3"
            }
          },
          {
            "player": {
              "id": 283,
              "name": "T. Alexander-Arnold",
              "number": 66,
              "pos": "D",
              "grid": "2:2"
            }
          },
          {
            "player": {
              "id": 300,
              "name": "G. Wijnaldum",
              "number": 5,
              "pos": "M",
              "grid": "2:1"
            }
          },
          {
            "player": {
              "id": 292,
              "name": "J. Henderson",
              "number": 14,
              "pos": "M",
              "grid": "3:3"
            }
          },
          {
            "player": {
              "id": 299,
              "name": "Fabinho",
              "number": 3,
              "pos": "D",
              "grid": "3:2"
            }
          },
          {
            "player": {
              "id": 294,
              "name": "N. Keïta",
              "number": 8,
              "pos": "M",
              "grid": "3:1"
            }
          },
          {
            "player": {
              "id": 302,
              "name": "Roberto Firmino",
              "number": 9,
              "pos": "F",
              "grid": "4:3"
            }
          },
          {
            "player": {
              "id": 306,
              "name": "Mohamed Salah",
              "number": 11,
              "pos": "F",
              "grid": "4:2"
            }
          },
          {
            "player": {
              "id": 304,
              "name": "S. Mané",
              "number": 10,
              "pos": "F",
              "grid": "4:1"
            }
          }
        ],
        "substitutes": [
          {
            "player": {
              "id": 507,
              "name": "Thiago Alcântara",
              "number": 6,
              "pos": "M",
              "grid": null
            }
          },
          {
            "player": {
              "id": 296,
              "name": "J. Milner",
              "number": 7,
              "pos": "M",
              "grid": null
            }
          },
          {
            "player": {
              "id": 1101,
              "name": "T. Minamino",
              "number": 18,
              "pos": "F",
              "grid": null
            }
          },
          {
            "player": {
              "id": 293,
              "name": "C. Jones",
              "number": 17,
              "pos": "M",
              "grid": null
            }
          },
          {
            "player": {
              "id": 305,
              "name": "D. Origi",
              "number": 27,
              "pos": "F",
              "grid": null
            }
          },
          {
            "player": {
              "id": 1600,
              "name": "K. Tsimikas",
              "number": 21,
              "pos": "D",
              "grid": null
            }
          },
          {
            "player": {
              "id": 18812,
              "name": "Adrián",
              "number": 13,
              "pos": "G",
              "grid": null
            }
          }
        ]
      }
    ]
  }
}